pysimdeum/__init__.py
pysimdeum/api.py
pysimdeum/core/__init__.py
pysimdeum/core/end_use.py
pysimdeum/core/house.py
pysimdeum/core/old_end_use.py
pysimdeum/core/statistics.py
pysimdeum/core/user.py
pysimdeum/core/utils.py
pysimdeum/data/__init__.py
pysimdeum/data/NL/__init__.py
pysimdeum/data/NL/diurnal_patterns.toml
pysimdeum/data/NL/household_statistics.toml
pysimdeum/data/NL/end_uses/BathroomTap.toml
pysimdeum/data/NL/end_uses/Bathtub.toml
pysimdeum/data/NL/end_uses/Dishwasher.toml
pysimdeum/data/NL/end_uses/KitchenTap.toml
pysimdeum/data/NL/end_uses/OutsideTap.toml
pysimdeum/data/NL/end_uses/Shower.toml
pysimdeum/data/NL/end_uses/WashingMachine.toml
pysimdeum/data/NL/end_uses/Wc.toml
pysimdeum/data/NL/end_uses/__init__.py
pysimdeum/data/NL/end_uses/pattern/__init__.py
pysimdeum/data/NL/end_uses/pattern/dp_kitchen_tap.txt
pysimdeum/data/NL/end_uses/pattern/pat_dishwasher.py
pysimdeum/data/NL/end_uses/pattern/pat_ktap.py
pysimdeum/data/NL/end_uses/pattern/pat_washing_machine.py
pysimdeum/tools/helper.py
pysimdeum/tools/plot.py
pysimdeum/tools/write.py
pysimdeum-1.0.1.dist-info/LICENSE
pysimdeum-1.0.1.dist-info/METADATA
pysimdeum-1.0.1.dist-info/WHEEL
pysimdeum-1.0.1.dist-info/top_level.txt
pysimdeum-1.0.1.dist-info/RECORD
