Metadata-Version: 2.1
Name: pysimdeum
Version: 1.0.1
Summary: A stochastic water demand end-use model in Python
Home-page: https://github.com/KWR-Water/pysimdeum
Author: David B. Steffelbauer
Author-email: david.steffelbauer@kompetenz-wasser.de
Maintainer: Bram Hillebrand
Maintainer-email: bram.hillebrand@kwrwater.nl
License: "EUPL"
Project-URL: Documentation, https://pysimdeum.readthedocs.io
Classifier: Development Status :: 4 - Beta
Classifier: Intended Audience :: Developers
Classifier: Topic :: Scientific/Engineering
Classifier: License :: OSI Approved :: European Union Public Licence 1.2 (EUPL 1.2)
Classifier: Programming Language :: Python :: 3.8
Classifier: Typing :: Typed
License-File: LICENSE
Requires-Dist: matplotlib
Requires-Dist: numpy
Requires-Dist: pandas
Requires-Dist: toml
Requires-Dist: xarray
Requires-Dist: scipy
